{
  "name": "Gokujou Smile",
  "group": "wug",
  "id": "gokusuma",
  "mp3": "sound/gokujou_smile.mp3",
  "ogg": "sound/gokujou_smile.ogg",
  "mapping": [
    {
      "range": [
        0.3,
        4
      ],
      "ans": [
        1,
        2,
        3,
        4,
        5,
        6,
        7
      ]
    },
    {
      "range": [
        17.7,
        20.4
      ],
      "ans": [
        5
      ]
    },
    {
      "range": [
        20.4,
        20.9
      ]
    },
    {
      "range": [
        20.9,
        23.9
      ],
      "ans": [
        1
      ]
    },
    {
      "range": [
        23.9,
        24.4
      ]
    },
    {
      "range": [
        24.4,
        29.5
      ],
      "ans": [
        2
      ]
    },
    {
      "range": [
        30.8,
        33.9
      ],
      "ans": [
        6
      ]
    },
    {
      "range": [
        33.9,
        34.4
      ]
    },
    {
      "range": [
        34.4,
        37.2
      ],
      "ans": [
        4
      ]
    },
    {
      "range": [
        37.2,
        37.8
      ]
    },
    {
      "range": [
        37.8,
        42.7
      ],
      "ans": [
        3
      ]
    },
    {
      "range": [
        43.2,
        49.9
      ],
      "ans": [
        7
      ]
    },
    {
      "range": [
        49.9,
        51
      ],
      "ans": [
        7
      ]
    },
    {
      "range": [
        51,
        54.5
      ],
      "ans": [
        4
      ]
    },
    {
      "range": [
        54.5,
        56.6
      ],
      "ans": [
        4
      ]
    },
    {
      "range": [
        56.6,
        63.5
      ],
      "ans": [
        5
      ]
    },
    {
      "range": [
        63.5,
        71
      ],
      "ans": [
        5
      ]
    },
    {
      "range": [
        71,
        74.2
      ],
      "ans": [
        1,
        2,
        3,
        4,
        5,
        6,
        7
      ]
    },
    {
      "range": [
        74.2,
        74.7
      ]
    },
    {
      "range": [
        74.7,
        77.9
      ],
      "ans": [
        2
      ]
    },
    {
      "range": [
        77.9,
        80.9
      ],
      "ans": [
        1,
        2,
        3,
        4,
        5,
        6,
        7
      ]
    },
    {
      "range": [
        80.9,
        81.4
      ]
    },
    {
      "range": [
        81.4,
        84.2
      ],
      "ans": [
        3
      ]
    },
    {
      "range": [
        84.7,
        87.6
      ],
      "ans": [
        1,
        2,
        3,
        4,
        5,
        6,
        7
      ]
    },
    {
      "range": [
        87.6,
        88.1
      ]
    },
    {
      "range": [
        88.1,
        91.2
      ],
      "ans": [
        7
      ]
    },
    {
      "range": [
        91.2,
        94.2
      ],
      "ans": [
        1,
        2,
        3,
        4,
        5,
        6,
        7
      ]
    },
    {
      "range": [
        94.2,
        94.7
      ]
    },
    {
      "range": [
        94.7,
        98
      ],
      "ans": [
        1,
        2,
        3,
        4,
        5,
        6,
        7
      ]
    },
    {
      "range": [
        104.8,
        107.8
      ],
      "ans": [
        2
      ]
    },
    {
      "range": [
        107.8,
        108.3
      ]
    },
    {
      "range": [
        108.3,
        111.1
      ],
      "ans": [
        7
      ]
    },
    {
      "range": [
        111.1,
        111.6
      ]
    },
    {
      "range": [
        111.6,
        116.8
      ],
      "ans": [
        6
      ]
    },
    {
      "range": [
        118.2,
        121.3
      ],
      "ans": [
        3
      ]
    },
    {
      "range": [
        121.3,
        121.8
      ]
    },
    {
      "range": [
        121.8,
        124.7
      ],
      "ans": [
        1
      ]
    },
    {
      "range": [
        124.7,
        125.2
      ]
    },
    {
      "range": [
        125.2,
        130.2
      ],
      "ans": [
        5
      ]
    },
    {
      "range": [
        130.2,
        137.1
      ],
      "ans": [
        7
      ]
    },
    {
      "range": [
        137.1,
        138.3
      ],
      "ans": [
        7
      ]
    },
    {
      "range": [
        138.3,
        141.7
      ],
      "ans": [
        1
      ]
    },
    {
      "range": [
        141.7,
        143.8
      ],
      "ans": [
        1
      ]
    },
    {
      "range": [
        143.8,
        150.7
      ],
      "ans": [
        3
      ]
    },
    {
      "range": [
        150.7,
        158.2
      ],
      "ans": [
        3
      ]
    },
    {
      "range": [
        158.2,
        161.6
      ],
      "ans": [
        1,
        2,
        3,
        4,
        5,
        6,
        7
      ]
    },
    {
      "range": [
        161.6,
        162.1
      ]
    },
    {
      "range": [
        162.1,
        165
      ],
      "ans": [
        6
      ]
    },
    {
      "range": [
        165,
        168.2
      ],
      "ans": [
        1,
        2,
        3,
        4,
        5,
        6,
        7
      ]
    },
    {
      "range": [
        168.2,
        168.7
      ]
    },
    {
      "range": [
        168.7,
        171.6
      ],
      "ans": [
        1
      ]
    },
    {
      "range": [
        172.1,
        174.9
      ],
      "ans": [
        1,
        2,
        3,
        4,
        5,
        6,
        7
      ]
    },
    {
      "range": [
        174.9,
        175.4
      ]
    },
    {
      "range": [
        175.4,
        178.5
      ],
      "ans": [
        4
      ]
    },
    {
      "range": [
        178.5,
        181.5
      ],
      "ans": [
        1,
        2,
        3,
        4,
        5,
        6,
        7
      ]
    },
    {
      "range": [
        181.5,
        182
      ]
    },
    {
      "range": [
        182,
        185.3
      ],
      "ans": [
        1,
        2,
        3,
        4,
        5,
        6,
        7
      ]
    },
    {
      "range": [
        212,
        215.7
      ],
      "ans": [
        1,
        2,
        3,
        4,
        5,
        6,
        7
      ]
    },
    {
      "range": [
        215.7,
        218.8
      ],
      "ans": [
        1,
        2,
        3,
        4,
        5,
        6,
        7
      ]
    },
    {
      "range": [
        218.8,
        222.3
      ],
      "ans": [
        1,
        2,
        3,
        4,
        5,
        6,
        7
      ]
    },
    {
      "range": [
        222.3,
        225.6
      ],
      "ans": [
        1,
        2,
        3,
        4,
        5,
        6,
        7
      ]
    },
    {
      "range": [
        225.6,
        228.7
      ],
      "ans": [
        1,
        2,
        3,
        4,
        5,
        6,
        7
      ]
    },
    {
      "range": [
        228.7,
        229.2
      ]
    },
    {
      "range": [
        229.2,
        232.1
      ],
      "ans": [
        1,
        2,
        3,
        4,
        5,
        6,
        7
      ]
    },
    {
      "range": [
        232.1,
        235.1
      ],
      "ans": [
        1,
        2,
        3,
        4,
        5,
        6,
        7
      ]
    },
    {
      "range": [
        235.1,
        235.6
      ]
    },
    {
      "range": [
        235.6,
        239
      ],
      "ans": [
        1,
        2,
        3,
        4,
        5,
        6,
        7
      ]
    }
  ],
  "slots": [
    {
      "command": "group",
      "members": [
        11,
        12
      ]
    },
    {
      "command": "group",
      "members": [
        13,
        14
      ]
    },
    {
      "command": "group",
      "members": [
        15,
        16
      ]
    },
    {
      "command": "group",
      "members": [
        39,
        40
      ]
    },
    {
      "command": "group",
      "members": [
        41,
        42
      ]
    },
    {
      "command": "group",
      "members": [
        43,
        44
      ]
    }
  ],
  "lyrics": [
    "{EGAO! GOKUJOU! SUMAIRU!}",
    "",
    "{KURAUDO ni kakareta SUKEJUURU} {(Yay!)}",
    "{Nandaka samishii shuumatsu wo} {(Yay!)}",
    "{Nandemo ii kara umerutte iu no ha chigau}",
    "",
    "{Honto jimi na no futsuu no hi ha} {(fu!)}",
    "{Douga de neko wo utsushitetari} {(fu!)}",
    "{Doudesho tamani ha heya no moyou ga he nanka ne}",
    "",
    "{Minna no shashin SURAIDO shite mita}",
    "{SUMAIRU} {ippai de zenkai de SUMAIRU darake de}",
    "{SUMAIRU? SUMAIRU?mairu}",
    "{Waratte shimau genki ni natta yo}",
    "{Akiramenai haru natsu aki fuyu no hi mo}",
    "",
    "{SHINDOI kisetsu wo shiteru kara} {(Whoo!)}",
    "{Kawaranu egao wo mederu}",
    "{NIPPON no egao ga uwagaki suru} {(Whoo!)}",
    "{Nanka tsurai toki mo}",
    "{NIPPON no egao ga kawaiku suru} {(Whoo!)}",
    "{Saki koboreru SAKURA iro}",
    "{SHINDOI kisetsu wo shitte koso no} {(Whoo!)}",
    "{Egao gokujou SUMAIRU}",
    "",
    "{Tenki ga ii hi ha dekakeyou} {(Yay!)}",
    "{Densha ni notte chotto toode shiyou} {(Yay!)}",
    "{Denenfuukei suteki na yasai mo toreru}",
    "",
    "{Choppiri nigate na mono datte} {(fu?)}",
    "{Oishii no tabetara suki ni naru} {(fu?)}",
    "{OIOI ima made shiranaide gomen to omou}",
    "",
    "{Umi ha hiroi yama mo sugoi}",
    "{MEIDO IN} {JAPAN ha saikou sa MAI MAI MAI SUTAA}",
    "{Nandatte umidaseru}",
    "{Asobi ni kite ai ni kite ne}",
    "{Kono hashi kara hashi made wo hashi no kuni he}",
    "",
    "{SHINDOI kisetsu wo shiteru kara} {(Whoo!)}",
    "{Kawaranu egao wo miseru}",
    "{NIPPON no egao ga uwagaki suru} {(Whoo!)}",
    "{Nanka tsurai toki mo}",
    "{NIPPON no egao ga motenashi suru} {(Whoo!)}",
    "{Saki koboreru SAKURA iro}",
    "{SHINDOI kisetsu wo shitte koso no} {(Whoo!)}",
    "{Egao gokujou SUMAIRU}",
    "",
    "{DONMAI namida wo shitteru kara}",
    "{Kawaranu egao wo mederu}",
    "{DONMAI na egao ga uwagaki suru}",
    "{Nanka tsurai toki mo}",
    "{DONMAI na egao ga kawaiku suru} {(Whoo!)}",
    "{Saki koboreru SAKURA iro}",
    "{DONMAI namida wo shitte koso no} {(Whoo!)}",
    "{Egao gokujou SUMAIRU }"
  ]
}
