{
  "name": "Hello, Hoshi o Kazoete",
  "group": "muse",
  "mp3": "sound/hello_hoshi_o_kazoete.mp3",
  "ogg": "sound/hello_hoshi_o_kazoete.ogg",
  "id": "hellohoshi",
  "mapping": [
    {
      "range": [
        0.6,
        18
      ],
      "ans": [
        5
      ]
    },
    {
      "range": [
        30,
        37
      ],
      "ans": [
        5
      ]
    },
    {
      "range": [
        38.5,
        42.5
      ],
      "ans": [
        6
      ]
    },
    {
      "range": [
        42.5,
        46.2
      ],
      "ans": [
        8
      ]
    },
    {
      "range": [
        46.6,
        48.5
      ],
      "ans": [
        6
      ]
    },
    {
      "range": [
        48.5,
        50.6
      ],
      "ans": [
        8
      ]
    },
    {
      "range": [
        50.6,
        52.7
      ],
      "ans": [
        5
      ]
    },
    {
      "range": [
        52,
        54
      ],
      "ans": [
        5,
        6,
        8
      ]
    },
    {
      "range": [
        55,
        73.6
      ],
      "ans": [
        5,
        6,
        8
      ]
    },
    {
      "range": [
        73.6,
        79
      ],
      "ans": [
        5
      ]
    },
    {
      "range": [
        79,
        84
      ],
      "ans": [
        5,
        6,
        8
      ]
    },
    {
      "range": [
        93.7,
        100.7
      ],
      "ans": [
        8
      ]
    },
    {
      "range": [
        102,
        109.7
      ],
      "ans": [
        6
      ]
    },
    {
      "range": [
        110.1,
        112.2
      ],
      "ans": [
        8
      ]
    },
    {
      "range": [
        112.2,
        114.2
      ],
      "ans": [
        5
      ]
    },
    {
      "range": [
        114.2,
        118.2
      ],
      "ans": [
        6
      ]
    },
    {
      "range": [
        118.6,
        120.7
      ],
      "ans": [
        8
      ]
    },
    {
      "range": [
        120.7,
        122.7
      ],
      "ans": [
        5
      ]
    },
    {
      "range": [
        122.7,
        127.2
      ],
      "ans": [
        6
      ]
    },
    {
      "range": [
        128,
        145
      ],
      "ans": [
        5,
        6,
        8
      ]
    },
    {
      "range": [
        162.8,
        172.9
      ],
      "ans": [
        5
      ]
    },
    {
      "range": [
        172.9,
        176
      ],
      "ans": [
        8
      ]
    },
    {
      "range": [
        176,
        180.3
      ],
      "ans": [
        6
      ]
    },
    {
      "range": [
        180.3,
        184.85
      ],
      "ans": [
        5
      ]
    },
    {
      "range": [
        184.85,
        189.7
      ],
      "ans": [
        8
      ]
    },
    {
      "range": [
        189,
        190.5
      ],
      "ans": [
        6
      ]
    },
    {
      "range": [
        190.8,
        192
      ],
      "ans": [
        5
      ]
    },
    {
      "range": [
        191.7,
        192.7
      ],
      "ans": [
        8
      ]
    },
    {
      "range": [
        192.4,
        193.4
      ],
      "ans": [
        5
      ]
    },
    {
      "range": [
        193.2,
        194.2
      ],
      "ans": [
        6
      ]
    },
    {
      "range": [
        193.7,
        196.3
      ],
      "ans": [
        5
      ]
    },
    {
      "range": [
        196.3,
        198
      ],
      "ans": [
        6,
        8
      ],
      "diff": 2
    },
    {
      "range": [
        198,
        202
      ],
      "ans": [
        5,
        6,
        8
      ]
    },
    {
      "range": [
        202,
        254
      ],
      "ans": [
        5,
        6,
        8
      ]
    }
  ]
}
