{
  "name": "Watashi no Symphony",
  "ogg": "sound/liella/watashi-no-symphony.ogg",
  "id": "watashi-no-symphony",
  "group": "liella",
  "name_jp": "私のSymphony",
  "language": "ja",
  "released": "2021-04-07",
  "album": "始まりは君の空",
  "added": "2026-05",
  "generated": "2026-05-02T06:28:40Z",
  "hidden": false,
  "slots": [],
  "lines": [
    {"lyric": "Takaramono o mitsuketa kodomo no you ni",
      "lyric_jp": "宝物を見つけた子どものように",
      "range": [0.99, 4.43], "ans": [1]},
    {"lyric": "Kanade hajimetanda yume o",
      "lyric_jp": "奏で始めたんだ 夢を",
      "range": [4.43, 7.71], "ans": [5]},
    {
      "lyric": "Kirari kibou hibikaseru no",
      "lyric_jp": "きらり希望 響かせるの",
      "parts": [
        {"lyric": "Kirari kibou",
          "lyric_jp": "きらり希望",
          "range": [7.71, 9.19], "ans": [3]},
        {"lyric": "Hibikaseru no",
          "lyric_jp": "響かせるの",
          "range": [8.74, 11.27], "ans": [4]}
      ]
    },
    {
      "lyric": "Dokomademo hirogare watashi no Symphony",
      "lyric_jp": "どこまでも広がれ 私のSymphony",
      "parts": [
        {"lyric": "Dokomademo hirogare",
          "lyric_jp": "どこまでも広がれ",
          "range": [11.27, 13.55], "ans": [2]},
        {"lyric": "Watashi no Symphony",
          "lyric_jp": "私のSymphony",
          "range": [13.1, 18.59], "ans": [1, 2, 3, 4, 5]}
      ]
    },
    "",
    {"lyric": "Zutto taisetsu ni shimatteta",
      "lyric_jp": "ずっと大切にしまってた",
      "range": [21.45, 24.92], "ans": [1]},
    {"lyric": "Ichiban daisuki na koto",
      "lyric_jp": "一番大好きなこと",
      "range": [24.92, 28.6], "ans": [1]},
    {"lyric": "Doushitara kanaerareru no?",
      "lyric_jp": "どうしたら叶えられるの？",
      "range": [28.6, 31.65], "ans": [1]},
    {"lyric": "Wakaranakute tachidomatte ita",
      "lyric_jp": "分からなくて立ち止まっていた",
      "range": [31.65, 35.91], "ans": [1]},
    {"lyric": "Chansu wa aru hi totsuzen Me",
      "lyric_jp": "チャンスはある日突然",
      "range": [35.91, 38.57], "ans": [2]},
    {"lyric": "No mae ni maiorite kita",
      "lyric_jp": "目の前に舞いおりてきた",
      "range": [38.57, 42.01], "ans": [2]},
    {"lyric": "Omou katachi to chigatte mo",
      "lyric_jp": "思うかたちと違っても",
      "range": [42.01, 45.36], "ans": [2]},
    {"lyric": "Sotto ryoute o nobashitanda",
      "lyric_jp": "そっと両手を伸ばしたんだ",
      "range": [45.36, 48.78], "ans": [2]},
    "",
    {"lyric": "Gikochi naku kizamu ippo ga",
      "lyric_jp": "ぎこちなく刻む一歩が",
      "range": [48.78, 52.19], "ans": [4]},
    {"lyric": "Patto azayaka ni sekai o kaeteku",
      "lyric_jp": "パッと鮮やかに世界を変えてく",
      "range": [52.19, 56.23], "ans": [3]},
    {"lyric": "Nani ga matsu no? Nani o yareru no?",
      "lyric_jp": "なにが待つの？ なにをやれるの？",
      "range": [56.23, 59.3], "ans": [5]},
    {"lyric": "Yuuki dashite susumou",
      "lyric_jp": "勇気出して進もう",
      "range": [59.3, 63.33], "ans": [1, 2, 3, 4, 5]},
    "",
    {"lyric": "Chippoke na kinou made no watashi janai",
      "lyric_jp": "ちっぽけな昨日までの私じゃない",
      "range": [63.33, 67.91], "ans": [1, 2, 3, 4, 5]},
    {"lyric": "Kanade hajimetanda yume o",
      "lyric_jp": "奏で始めたんだ 夢を",
      "range": [67.91, 71.11], "ans": [1, 2, 3, 4, 5]},
    {"lyric": "Maku ga agaru koko kara saki wa",
      "lyric_jp": "幕があがる ここから先は",
      "range": [71.11, 74.48], "ans": [4]},
    {"lyric": "Mune ni egaiteta suteeji",
      "lyric_jp": "胸に描いてたステージ",
      "range": [74.48, 77.7], "ans": [3]},
    "",
    {"lyric": "Dekikkonai yotte omotteta koto mo",
      "lyric_jp": "できっこないよって思ってたことも",
      "range": [77.7, 81.65], "ans": [1, 2, 3, 4, 5]},
    {"lyric": "Fumidaseba hora kanaunda",
      "lyric_jp": "踏みだせばほら叶うんだ",
      "range": [81.65, 84.85], "ans": [1, 2, 3, 4, 5]},
    {"lyric": "Kirari kibou hibikaseru no",
      "lyric_jp": "きらり希望 響かせるの",
      "range": [84.85, 88.45], "ans": [5]},
    {
      "lyric": "Dokomademo hirogare watashi no Symphony",
      "lyric_jp": "どこまでも広がれ 私のSymphony",
      "parts": [
        {"lyric": "Dokomademo hirogare",
          "lyric_jp": "どこまでも広がれ",
          "range": [88.45, 90.71], "ans": [1]},
        {"lyric": "Watashi no Symphony",
          "lyric_jp": "私のSymphony",
          "range": [90.26, 95.39], "ans": [1, 2, 3, 4, 5]}
      ]
    },
    "",
    {"lyric": "Guzuguzu shiteta kako ni",
      "lyric_jp": "グズグズしてた過去に",
      "range": [99.15, 101.98], "ans": [4]},
    {"lyric": "Messeeji o okureru no nara",
      "lyric_jp": "メッセージを送れるのなら",
      "range": [101.98, 105.7], "ans": [4]},
    {"lyric": "Ima wa tanoshii yo\" tte iitai!",
      "lyric_jp": "「今は楽しいよ」って言いたい！",
      "range": [105.7, 109.04], "ans": [3]},
    {"lyric": "Datte konna ni takanatteru yo",
      "lyric_jp": "だってこんなに高鳴ってるよ",
      "range": [109.04, 112.43], "ans": [3]},
    "",
    {"lyric": "Nandemo dekisou na anoko mo",
      "lyric_jp": "なんでもできそうなあの子も",
      "range": [112.43, 115.78], "ans": [1]},
    {"lyric": "Itsumo warai tayasanai anoko mo",
      "lyric_jp": "いつも笑い絶やさないあの子も",
      "range": [115.78, 119.43], "ans": [5]},
    {"lyric": "Mayoi nagara tomadoi nagara",
      "lyric_jp": "迷いながら 戸惑いながら",
      "range": [119.43, 122.6], "ans": [2]},
    {"lyric": "Kitto yume o miteru",
      "lyric_jp": "きっと夢をみてる",
      "range": [122.6, 126.62], "ans": [1, 2, 3, 4, 5]},
    "",
    "[next-col]",
    {"lyric": "Totte oki no watashi rashii fureezu o",
      "lyric_jp": "とっておきの私らしいフレーズを",
      "range": [126.62, 131.43], "ans": [1, 2, 3, 4, 5]},
    {"lyric": "Itsuka mitsukerareru you ni",
      "lyric_jp": "いつか見つけられるように",
      "range": [131.43, 134.69], "ans": [1, 2, 3, 4, 5]},
    {"lyric": "Hajimete demo chousen shite wa",
      "lyric_jp": "初めてでも挑戦しては",
      "range": [134.69, 138.31], "ans": [5]},
    {"lyric": "Inoru no douka todoite!",
      "lyric_jp": "祈るの どうか届いて！",
      "range": [138.31, 141.16], "ans": [2]},
    "",
    {"lyric": "Haruka tooku de nagareteru merodi",
      "lyric_jp": "遥か遠くで流れてるメロディ",
      "range": [141.16, 145.09], "ans": [1, 2, 3, 4, 5]},
    {"lyric": "Kobosazu mimi o sumashite",
      "lyric_jp": "こぼさず耳を澄まして",
      "range": [145.09, 148.43], "ans": [1, 2, 3, 4, 5]},
    {"lyric": "Shiranai tobira akete yukou",
      "lyric_jp": "知らない扉 開けてゆこう",
      "range": [148.43, 151.88], "ans": [4]},
    {
      "lyric": "Itsumademo owarasenai yo Symphony",
      "lyric_jp": "いつまでも終わらせないよSymphony",
      "parts": [
        {"lyric": "Itsumademo owarasenai yo",
          "lyric_jp": "いつまでも終わらせないよ",
          "range": [151.88, 155.5], "ans": [3]},
        {"lyric": "Symphony",
          "lyric_jp": "Symphony",
          "range": [155.05, 158.76], "ans": [1, 2, 3, 4, 5]}
      ]
    },
    "",
    {"lyric": "Migite no koyubi to hidarite no koyubi o musunde",
      "lyric_jp": "右手の小指と左手の小指をむすんで",
      "range": [169.06, 175.75], "ans": [2]},
    {"lyric": "Jibun ni yakusoku shiyou",
      "lyric_jp": "自分に約束しよう",
      "range": [175.75, 179.23], "ans": [5]},
    {"lyric": "Kyou no kimochi zutto wasurenai yo",
      "lyric_jp": "今日の気持ちずっと忘れないよ",
      "range": [179.23, 184.95], "ans": [1, 2, 3, 4, 5]},
    "",
    {"lyric": "Chippoke na kinou made no watashi janai",
      "lyric_jp": "ちっぽけな昨日までの私じゃない",
      "range": [184.95, 189.64], "ans": [1]},
    {"lyric": "Kanade hajimetanda yume o",
      "lyric_jp": "奏で始めたんだ 夢を",
      "range": [189.64, 193.0], "ans": [1]},
    {"lyric": "Maku ga agaru koko kara saki wa",
      "lyric_jp": "幕があがる ここから先は",
      "range": [193.0, 196.36], "ans": [2]},
    {"lyric": "Mune ni egaiteta suteeji",
      "lyric_jp": "胸に描いてたステージ",
      "range": [196.36, 199.57], "ans": [5]},
    "",
    {"lyric": "Dekikkonai yotte omotteta koto mo",
      "lyric_jp": "できっこないよって思ってたことも",
      "range": [199.57, 203.41], "ans": [1, 2, 3, 4, 5]},
    {"lyric": "Fumidaseba hora kanaunda",
      "lyric_jp": "踏みだせばほら叶うんだ",
      "range": [203.41, 206.68], "ans": [1, 2, 3, 4, 5]},
    {
      "lyric": "Kirari kibou hibikaseru no",
      "lyric_jp": "きらり希望 響かせるの",
      "parts": [
        {"lyric": "Kirari kibou",
          "lyric_jp": "きらり希望",
          "range": [206.68, 208.04], "ans": [4]},
        {"lyric": "Hibikaseru no",
          "lyric_jp": "響かせるの",
          "range": [207.59, 210.15], "ans": [3]}
      ]
    },
    {"lyric": "Dokomademo hirogatteke",
      "lyric_jp": "どこまでも広がってけ",
      "range": [210.15, 213.81], "ans": [1, 2, 3, 4, 5]},
    "",
    {"lyric": "Rarara rarara rarara saa!",
      "lyric_jp": "ラララ ラララ ラララ さあ！",
      "range": [213.81, 217.23], "ans": [1, 2, 3, 4, 5]},
    {"lyric": "Rarara rarara rarara",
      "lyric_jp": "ラララ ラララ ラララ",
      "range": [217.23, 219.71], "ans": [1, 2, 3, 4, 5]},
    {"lyric": "Atarashii watashi Ima, hajimaru yo Symphony",
      "lyric_jp": "新しい私 今、始まるよSymphony",
      "range": [219.71, 229.57], "ans": [1, 2, 3, 4, 5]}
  ]
}
