{
  "name": "BLOOM OF COLORS",
  "ogg": "sound/bloom_of_colors.ogg",
  "id": "bloom-of-colors",
  "group": "aqours",
  "added": "2026-04",
  "hidden": false,
  "slots": [

  ],
  "lines": [
    {"lyric": "Ippai no dekigoto ga ima wo irodotte irunda ne",
      "lyric_jp": "Ippai no dekigoto ga ima wo irodotte irunda ne",
      "range": [13, 20.5], "ans": [6]},
    {"lyric": "Ichimai no kyanbasu e nando mo iro wo kasanete yuku",
      "lyric_jp": "Ichimai no KYANBASU e nando mo iro wo kasanete yuku",
      "range": [20.5, 27.5], "ans": [6]},
    {"lyric": "Kinou wa kinou iro",
      "lyric_jp": "Kinou wa kinou iro",
      "range": [27.5, 31], "ans": [2]},
    {"lyric": "Asu wa asu iro",
      "lyric_jp": "Asu wa asu iro",
      "range": [31, 34.5], "ans": [6]},
    {"lyric": "Kawatte yuku koto",
      "lyric_jp": "Kawatte yuku koto",
      "range": [34.5, 38.5], "ans": [2]},
    {"lyric": "Tanoshimeru you ni natta yo",
      "lyric_jp": "Tanoshimeru you ni natta yo",
      "range": [38.5, 44.13], "ans": [6]},
    "",
    {"lyric": "Kitto ii koto bakka janai",
      "lyric_jp": "Kitto ii koto bakka janai",
      "range": [44.13, 48.08], "ans": [3]},
    {"lyric": "Konnan no hou ga ooi kamo ne",
      "lyric_jp": "Konnan no hou ga ooi kamo ne",
      "range": [48.08, 52.5], "ans": [1]},
    {"lyric": "Soredemo mae wo muite susunde iku",
      "lyric_jp": "Soredemo mae wo muite susunde iku",
      "range": [52.5, 57.5], "ans": [1]},
    {"lyric": "Ippo ippo omoide wo daite",
      "lyric_jp": "Ippo ippo omoide wo daite",
      "range": [57.5, 62.5], "ans": [1, 7]},
    "",
    {"lyric": "Kyou mo, kyou wo ikiru bokura de (Wow Wow~ bokura nara)",
      "lyric_jp": "Kyou mo, kyou wo ikiru bokura de (Wow Wow~ bokura nara)",
      "range": [62.5, 67.6], "ans": []},
    {"lyric": "Irotoridori wo sakaseyou (Wow~)",
      "lyric_jp": "Irotoridori wo sakaseyou (Wow~)",
      "range": [67.6, 72.5], "ans": []},
    {"lyric": "Shizen to mirai made hirakeru yo (Oh~ saa)",
      "lyric_jp": "Shizen to MIRAI made hirakeru yo (Oh~ saa)",
      "range": [72.5, 78], "ans": []},
    {"lyric": "Atarashii koto hajimaru yokan! (Hajimaru)",
      "lyric_jp": "Atarashii koto hajimaru yokan! (hajimaru)",
      "range": [78, 84], "ans": []},
    "",
    {"lyric": "Mou kowai mono nante nai sa (Wow Wow~ daijoubu)",
      "lyric_jp": "Mou kowai mono nante nai sa (Wow Wow~ daijoubu)",
      "range": [84, 89.5], "ans": []},
    {"lyric": "Kakegaenai minna ga iru (kakegaenai)",
      "lyric_jp": "Kakegaenai minna ga iru (kakegaenai)",
      "range": [89.5, 94.5], "ans": []},
    {"lyric": "Kimi mo issho da yo!",
      "lyric_jp": "Kimi mo issho da yo!",
      "range": [94.5, 97.58], "ans": []},
    {"lyric": "Mune no oku de zutto iroasenai",
      "lyric_jp": "Mune no oku de zutto iroasenai",
      "range": [97.58, 103], "ans": []},
    {"lyric": "Bloom OF colors",
      "lyric_jp": "BLOOM OF COLORS",
      "range": [103, 110.5], "ans": []},
    "",
    {"lyric": "Shikkari shinakucha tte tsui asette karamawatte",
      "lyric_jp": "Shikkari shinakucha tte tsui asette karamawatte",
      "range": [110.5, 119.5], "ans": [5]},
    {"lyric": "Kou iu toki kimi wa nante iu darou? Omoi ukabete miru",
      "lyric_jp": "Kou iu toki kimi wa nante iu darou? Omoi ukabete miru",
      "range": [119.5, 127.5], "ans": [3]},
    {"lyric": "Kioku no umi de oshaberi shiyou yo",
      "lyric_jp": "Kioku no umi de oshaberi shiyou yo",
      "range": [127.5, 134], "ans": [7]},
    {"lyric": "Kawatte yuku kedo kawaranai de iyou ne",
      "lyric_jp": "Kawatte yuku kedo kawaranai de iyou ne",
      "range": [134, 141], "ans": [2]},
    "",
    "[next-col]",
    {"lyric": "Kitto te wo hanashite mo sugu soba ni kanjiaeru",
      "lyric_jp": "Kitto te wo hanashite mo sugu soba ni kanjiaeru",
      "range": [141, 149.64], "ans": [4]},
    {"lyric": "Sou desho? Kokoro de tsunagatteru",
      "lyric_jp": "Sou desho? Kokoro de tsunagatteru",
      "range": [149.64, 155], "ans": [5]},
    {"lyric": "Shinpai nante hitotsu mo nai ne",
      "lyric_jp": "Shinpai nante hitotsu mo nai ne",
      "range": [155, 161], "ans": []},
    "",
    {"lyric": "Kyou mo, kyou wo ikiru bokura de",
      "lyric_jp": "Kyou mo, kyou wo ikiru bokura de",
      "range": [161, 166.5], "ans": [6]},
    {"lyric": "(Wow Wow~ bokura nara)",
      "range": [164.5, 166.5], "ans": []},
    {"lyric": "(Wow Wow~ bokura nara)",
      "lyric_jp": "(Wow Wow~ bokura nara)",
      "range": [166.5, 166.5], "ans": []},
    {"lyric": "Yakusoku no merodii kanadeyou",
      "lyric_jp": "Yakusoku no merodii kanadeyou",
      "range": [166.5, 170.76], "ans": [6]},
    {"lyric": "(Wow~)",
      "range": [168.76, 170.76], "ans": []},
    {"lyric": "(Wow~)",
      "lyric_jp": "(Wow~)",
      "range": [170.76, 171], "ans": []},
    {"lyric": "Utagoe wa tooku e dokomademo",
      "lyric_jp": "Utagoe wa tooku e dokomademo",
      "range": [171, 176.5], "ans": [6]},
    {"lyric": "(Oh~ saa)",
      "range": [174.5, 176.5], "ans": []},
    {"lyric": "(Oh~ saa)",
      "lyric_jp": "(Oh~ saa)",
      "range": [176.5, 176.5], "ans": []},
    {"lyric": "Kono sekai wo yasashiku dekiru",
      "lyric_jp": "Kono sekai wo yasashiku dekiru",
      "range": [176.5, 181.5], "ans": [6]},
    {"lyric": "(yasashiku)",
      "range": [179.5, 181.5], "ans": []},
    {"lyric": "(yasashiku)",
      "lyric_jp": "(yasashiku)",
      "range": [181.5, 182], "ans": []},
    "",
    {"lyric": "Mou kowai mono nante nai sa (Wow Wow~ daijoubu)",
      "lyric_jp": "Mou kowai mono nante nai sa (Wow Wow~ daijoubu)",
      "range": [182, 187.44], "ans": []},
    {"lyric": "Kakegaenai minna ga iru (kakegaenai)",
      "lyric_jp": "Kakegaenai minna ga iru (kakegaenai)",
      "range": [187.44, 192.5], "ans": []},
    {"lyric": "Kimi mo issho da yo!",
      "lyric_jp": "Kimi mo issho da yo!",
      "range": [192.5, 196], "ans": []},
    {"lyric": "Mune no oku de zutto iroasenai",
      "lyric_jp": "Mune no oku de zutto iroasenai",
      "range": [196, 202], "ans": []},
    {"lyric": "Bloom OF colors",
      "lyric_jp": "BLOOM OF COLORS",
      "range": [202, 210], "ans": []},
    "",
    {"lyric": "(Koe awasete)",
      "lyric_jp": "(Koe awasete)",
      "range": [210, 214.5], "ans": [1, 2, 3, 4, 5, 7, 8, 9]},
    {"lyric": "Bokura issho da yo",
      "lyric_jp": "Bokura issho da yo",
      "range": [214.5, 219.5], "ans": [6]},
    {"lyric": "(Hitotsu ni)",
      "lyric_jp": "(Hitotsu ni)",
      "range": [219.5, 223.5], "ans": [1, 2, 3, 4, 5, 7, 8, 9]},
    {"lyric": "Itsumademo zutto",
      "lyric_jp": "Itsumademo zutto",
      "range": [223.5, 228.5], "ans": [2]},
    {"lyric": "(Koe awasete)",
      "lyric_jp": "(Koe awasete)",
      "range": [228.5, 232.5], "ans": [1, 2, 3, 4, 5, 7, 8, 9]},
    {"lyric": "Iro wo kasanete ikou",
      "lyric_jp": "Iro wo kasanete ikou",
      "range": [232.5, 240], "ans": [6]},
    {"lyric": "(Hitotsu ni)",
      "lyric_jp": "(Hitotsu ni)",
      "range": [240, 244.5], "ans": [1, 2, 3, 4, 5, 7, 8, 9]},
    {"lyric": "Bloom OF colors",
      "lyric_jp": "BLOOM OF COLORS",
      "range": [244.5, 265.37], "ans": [6]}
  ]
}
