{
  "name": "smile smile ship Start!",
  "ogg": "sound/smile_smile_ship_start.ogg",
  "id": "smile-smile-ship-start",
  "group": "aqours",
  "released": "2021-03-31",
  "added": "2026-04",
  "hidden": false,
  "slots": [

  ],
  "generated": "2026-04-15T01:44:49Z",
  "lines": [
    {
      "lyric_jp": "彼方を目指したいって？",
      "parts": [
        {"lyric": "(Hey! Hey!)",
          "range": [29.76, 30.3], "ans": []},
        {"lyric": "(Hey! Hey!)",
          "range": [30.3, 30.64], "ans": []},
        {"lyric": "(Hey! Hey!)",
          "range": [30.44, 30.94], "ans": []},
        {"lyric": "(1, 2, 3!)",
          "range": [30.74, 31.23], "ans": []},
        {"lyric": "Kanata wo mezashitai tte?",
          "range": [30.79, 32.32], "ans": [1]}
      ]
    },
    "",
    {"lyric": "Noranakucha da",
      "lyric_jp": "乗らなくちゃだ",
      "range": [32.14, 33.21], "ans": [1]},
    {
      "lyric_jp": "Wonder trip (All right!)",
      "parts": [
        {"lyric": "Wonder trip",
          "range": [33.21, 34.34], "ans": [1]},
        {"lyric": "(Alright!)",
          "range": [33.7, 34.44], "ans": [4, 5, 6]}
      ]
    },
    {"lyric": "Kitai de mappu egakou",
      "lyric_jp": "期待でマップ描こう",
      "range": [34.2, 36.16], "ans": [1]},
    {
      "lyric_jp": "凄い 凄い 凄い楽しいっ",
      "parts": [
        {"lyric": "Sugoi sugoi sugoi tanoshii",
          "range": [36.16, 38.57], "ans": [1]},
        {"lyric": "(Hey!)",
          "range": [37.87, 38.82], "ans": []}
      ]
    },
    "",
    {"lyric": "Matsu no wa nigate nanda",
      "lyric_jp": "待つのは苦手なんだ",
      "range": [38.82, 41.05], "ans": [2]},
    {"lyric": "Sugu ikou yo",
      "lyric_jp": "すぐ行こうよ",
      "range": [41.05, 42.36], "ans": [2]},
    {
      "lyric_jp": "Wonder trip (Hurry up!)",
      "parts": [
        {"lyric": "Wonder trip",
          "range": [42.36, 43.55], "ans": [2]},
        {"lyric": "(Hurry up!)",
          "range": [42.93, 43.78], "ans": [4, 5, 6]}
      ]
    },
    {"lyric": "Paatii hiraichaeba? Dansu!",
      "lyric_jp": "パーティー開いちゃえば？ダンス！",
      "range": [43.65, 45.56], "ans": [3]},
    {
      "lyric_jp": "ミライ ミライ ミライへステップ",
      "parts": [
        {"lyric": "Mirai mirai mirai e no suteppu",
          "range": [45.56, 47.91], "ans": [3]},
        {"lyric": "(mirai e no suteppu)",
          "range": [47.21, 48.16], "ans": [4, 5, 6]}
      ]
    },
    "",
    {"lyric": "Mainichi umarekawaru aoi sora ni wa",
      "lyric_jp": "毎日生まれ変わる青い空は",
      "range": [48.16, 52.14], "ans": [7]},
    {"lyric": "Nandemo nandomo yume wo katarou",
      "lyric_jp": "なんでもなんども 夢を語ろう",
      "range": [52.14, 54.57], "ans": [6]},
    {"lyric": "Muri muri iwazu ni yatte waraou",
      "lyric_jp": "ムリムリ言わずに やって笑おう",
      "range": [54.57, 57.61], "ans": [6]},
    {
      "lyric_jp": "誰もがきっと（まっすぐに）向かいあうんだね",
      "parts": [
        {"lyric": "Daremo ga kitto",
          "range": [57.61, 60.35], "ans": [8]},
        {"lyric": "(massugu ni)",
          "range": [59.65, 61.18], "ans": [4, 5, 6]},
        {"lyric": "Mukaiaunda ne",
          "range": [60.48, 61.84], "ans": [8]}
      ]
    },
    {
      "lyric_jp": "強い 願い 隠さずに Let's go!（ワン・ツー・スリー！）",
      "parts": [
        {"lyric": "Tsuyoi negai kakusazu ni Let’s go!",
          "range": [61.84, 64.52], "ans": [4]},
        {"lyric": "(WANeTSUUeSURII!)",
          "range": [63.84, 65.03], "ans": [5]}
      ]
    },
    {"lyric": "Sunao ga ichiban da!",
      "lyric_jp": "素直がイチバンだ！",
      "range": [64.82, 67.44], "ans": [9]},
    "",
    {"lyric": "(Hey! Hey!) nami yo utae",
      "lyric_jp": "波よ歌え",
      "range": [67.44, 69], "ans": []},
    {
      "lyric_jp": "エブリバディ！歌えば始まる",
      "parts": [
        {"lyric": "Eburibadi!",
          "range": [69, 70.14], "ans": [4, 5, 6]},
        {"lyric": "Utaeba hajimaru",
          "range": [69.44, 71.22], "ans": []}
      ]
    },
    {"lyric": "(Hey! Hey!) atarashii funade mo kimi ga irunda yo",
      "lyric_jp": "新しい船でも君がいるんだよ",
      "range": [71.22, 75.85], "ans": []},
    {"lyric": "(Hey! Hey!) utaeba kaze no naka",
      "lyric_jp": "歌えば風の中",
      "range": [75.85, 78.14], "ans": []},
    {
      "lyric_jp": "ほら！ほら！呼ばれてるんだよ",
      "parts": [
        {"lyric": "Hora! Hora!",
          "range": [78.14, 79.19], "ans": [4, 5, 6]},
        {"lyric": "Yobareterunda yo",
          "range": [78.49, 80.4], "ans": []}
      ]
    },
    {"lyric": "(Hey! Hey!) shio no kaori suikonde mita",
      "lyric_jp": "潮の香り 吸い込んでみた",
      "range": [80.4, 85.12], "ans": []},
    {
      "lyric_jp": "希望と言う帆を揚げて smile smile ship Start!",
      "parts": [
        {"lyric": "Kibou to iu ho wo agete",
          "range": [85.12, 87.59], "ans": [1]},
        {"lyric": "Smile smile ship Start!",
          "range": [86.89, 91.12], "ans": []},
        {"lyric": "(Hey! Hey!)",
          "range": [91.12, 91.72], "ans": []}
      ]
    },
    "",
    {
      "lyric_jp": "海路は目に見えないって？",
      "parts": [
        {"lyric": "(Hey! Hey!)",
          "range": [99.42, 100.02], "ans": []},
        {"lyric": "(Hey! Hey!)",
          "range": [100.02, 100.97], "ans": []},
        {"lyric": "Kairo wa me ni mienai tte?",
          "range": [100.27, 103.03], "ans": [9]}
      ]
    },
    "",
    {"lyric": "Sorya souda yo",
      "lyric_jp": "そりゃそうだよ",
      "range": [103.03, 103.98], "ans": [9]},
    {
      "lyric_jp": "Danger trip (Oh boy!)",
      "parts": [
        {"lyric": "Danger trip",
          "range": [103.98, 104.98], "ans": [9]},
        {"lyric": "(Oh boy!)",
          "range": [104.28, 105.06], "ans": [4, 5, 6]}
      ]
    },
    {"lyric": "Dakara omoshiroin janai",
      "lyric_jp": "だから面白いんじゃない",
      "range": [105.06, 107.47], "ans": [9]},
    {
      "lyric_jp": "気合い 気合い 気合い入れよっ",
      "parts": [
        {"lyric": "Kiai kiai kiai ire yo",
          "range": [107.47, 109.63], "ans": [9]},
        {"lyric": "(Hey!)",
          "range": [108.93, 109.88], "ans": []}
      ]
    },
    "",
    {"lyric": "Haretara sakki okkaketa",
      "lyric_jp": "晴れたらさっき追いかけた",
      "range": [109.88, 112.22], "ans": [8]},
    {
      "lyric_jp": "鳥が帽子持ってく（返して〜！）",
      "parts": [
        {"lyric": "Tori ga boushi motteku",
          "range": [112.22, 114.33], "ans": [8]},
        {"lyric": "(kaeshite~!)",
          "range": [113.63, 114.54], "ans": [4, 5, 6]}
      ]
    },
    {"lyric": "Nante jiyuu ni tobu no",
      "lyric_jp": "なんて自由に飛ぶの",
      "range": [114.1, 116.73], "ans": [7]},
    {
      "lyric_jp": "ズルイ ズルイ ズルイ... カッコイイ",
      "parts": [
        {"lyric": "Zurui zurui zurui... kakkoii",
          "range": [116.73, 118.88], "ans": [7]},
        {"lyric": "(zurui... kakkoid)",
          "range": [118.18, 119.13], "ans": [4, 5, 6]}
      ]
    },
    "",
    {"lyric": "Ase ga ochiru to issho ni mayoi mo kiete",
      "lyric_jp": "汗が落ちると一緒に迷いも消えて",
      "range": [119.13, 123.19], "ans": [3]},
    {"lyric": "Ikioi tsuita yo mou tomaranai",
      "lyric_jp": "勢いついたよ も止まらない",
      "range": [123.19, 125.37], "ans": [5]},
    {"lyric": "Dasshu & janpu da So sky high",
      "lyric_jp": "ダッシュ＆ジャンプだ So sky high",
      "range": [125.37, 128.36], "ans": [5]},
    {
      "lyric_jp": "誰かの声が（準備できた！）聞こえたから",
      "parts": [
        {"lyric": "Dareka no koe ga",
          "range": [128.36, 130.44], "ans": [1]},
        {"lyric": "(junbi dekita!)",
          "range": [129.74, 131.68], "ans": [4, 5, 6]},
        {"lyric": "Kikoeta kara",
          "range": [130.98, 132.82], "ans": [1]}
      ]
    },
    {
      "lyric_jp": "返事するよ みんなも行くよ（ワン・ツー・スリー！）",
      "parts": [
        {"lyric": "Henji suru yo minna mo iku yo",
          "range": [132.82, 135.17], "ans": [4]},
        {"lyric": "(WANeTSUUeSURII!)",
          "range": [134.73, 135.96], "ans": [6]}
      ]
    },
    {"lyric": "Susundeku yo genki ni!",
      "lyric_jp": "進んでくよゲンキに！",
      "range": [135.66, 138.19], "ans": [2]},
    "",
    {"lyric": "(Hey! Hey!) boku mo utau",
      "lyric_jp": "僕も歌う",
      "range": [138.19, 139.71], "ans": []},
    {
      "lyric_jp": "エブリバディ！歌ってるとさ",
      "parts": [
        {"lyric": "Eburibadi!",
          "range": [139.71, 141.01], "ans": [4, 5, 6]},
        {"lyric": "Utatteru to sa",
          "range": [140.31, 142.27], "ans": []}
      ]
    },
    {"lyric": "(Hey! Hey!) sekai wa kirei na bouken wo misebirakasunda",
      "lyric_jp": "世界はキレイな冒険を見せびらかすんだ",
      "range": [142.27, 146.81], "ans": []},
    {"lyric": "(Hey! Hey!) utaeba omoidasu",
      "lyric_jp": "歌えば思い出す",
      "range": [146.81, 148.93], "ans": []},
    {
      "lyric_jp": "まだ！まだ！あきらめないと",
      "parts": [
        {"lyric": "Mada! Mada!",
          "range": [148.93, 149.93], "ans": [4, 5, 6]},
        {"lyric": "Akiramenai to",
          "range": [149.23, 151.38], "ans": []}
      ]
    },
    {"lyric": "(Hey! Hey!) oikakeru jibun de itai yo",
      "lyric_jp": "おいかける自分でいたいよ",
      "range": [151.38, 155.76], "ans": []},
    {
      "lyric_jp": "夢まとう帆を揚げて smile smile ship Start!",
      "parts": [
        {"lyric": "Yume matou ho wo agete",
          "range": [155.76, 158.02], "ans": []},
        {"lyric": "Smile smile ship Start!",
          "range": [158.02, 162.58], "ans": []}
      ]
    },
    "",
    "[next-col]",
    {"lyric": "Kanata ni nani ga nani ga kanata ni?",
      "lyric_jp": "彼方に何が 何が彼方に？",
      "range": [164.73, 166.4], "ans": [1]},
    {
      "lyric_jp": "いつかの星が誘いかける 新たに",
      "parts": [
        {"lyric": "Itsuka no hoshi ga sasoikakeru arata ni",
          "range": [166.4, 179.85], "ans": [1]},
        {"lyric": "(Hey! Hey!)",
          "range": [179.15, 180.1], "ans": []}
      ]
    },
    "",
    {
      "lyric_jp": "歌いたいから（歌いたいから）",
      "parts": [
        {"lyric": "(Hey! Hey!)",
          "range": [180.1, 180.75], "ans": []},
        {"lyric": "(Hey! Hey!)",
          "range": [180.75, 181.25], "ans": []},
        {"lyric": "(Hey! Hey!)",
          "range": [180.96, 181.52], "ans": []},
        {"lyric": "Utaitai kara",
          "range": [181.01, 181.98], "ans": [2, 3], "diff": 2},
        {"lyric": "(Utaitai kara)",
          "range": [181.64, 182.65], "ans": [1, 6, 7], "diff": 2}
      ]
    },
    "",
    {
      "lyric_jp": "歌ってるよ（歌ってるよ）",
      "parts": [
        {"lyric": "Utatteru yo",
          "range": [181.99, 184.05], "ans": [4, 5], "diff": 2},
        {"lyric": "(Utatteru yo)",
          "range": [184.31, 185.05], "ans": [1, 6, 7], "diff": 2}
      ]
    },
    {
      "lyric_jp": "伝われば",
      "parts": [
        {"lyric": "Tsutawareba",
          "range": [184.34, 186.03], "ans": [8, 9], "diff": 2},
        {"lyric": "(tsutawareba kasanatteku)",
          "range": [185.33, 186.28], "ans": [1, 6, 7], "diff": 2}
      ]
    },
    {"lyric": "Kokoro kasanatteku",
      "lyric_jp": "ココロ重なってく",
      "range": [186.28, 189.2], "ans": [8, 9], "diff": 2},
    {"lyric": "Yurarete hitotsu ni naritai",
      "lyric_jp": "揺られてひとつになりたい",
      "range": [189.2, 193.35], "ans": [2, 3], "diff": 2},
    {
      "lyric_jp": "そしてもっと 楽しくなりたいね",
      "parts": [
        {"lyric": "Soshite motto",
          "range": [193.35, 195.68], "ans": [4, 5], "diff": 2},
        {"lyric": "Tanoshiku naritai ne",
          "range": [194.98, 199.79], "ans": [8, 9], "diff": 2}
      ]
    },
    {"lyric": "Egao de tanoshiku ne!",
      "lyric_jp": "笑顔で楽しくね！",
      "range": [199.79, 201.99], "ans": [1, 6, 7], "diff": 2},
    "",
    {"lyric": "(Hey! Hey!) nami yo utae",
      "lyric_jp": "波よ歌え",
      "range": [201.99, 203.83], "ans": []},
    {
      "lyric_jp": "エブリバディ！歌えば始まる",
      "parts": [
        {"lyric": "Eburibadi!",
          "range": [203.83, 204.98], "ans": [4, 5, 6]},
        {"lyric": "Utaeba hajimaru",
          "range": [204.28, 206.28], "ans": []}
      ]
    },
    {"lyric": "(Hey! Hey!) atarashii funade mo kimi ga irunda yo",
      "lyric_jp": "新しい船出も君がいるんだよ",
      "range": [206.28, 211.13], "ans": []},
    {"lyric": "(Hey! Hey!) utaeba kaze no naka",
      "lyric_jp": "歌えば風の中",
      "range": [211.13, 212.82], "ans": []},
    {
      "lyric_jp": "ほら！ほら！呼ばれてるんだよ",
      "parts": [
        {"lyric": "Hora! Hora!",
          "range": [212.82, 214.06], "ans": [4, 5, 6]},
        {"lyric": "Yobareterunda yo",
          "range": [213.36, 215.43], "ans": []}
      ]
    },
    {
      "lyric_jp": "潮の香り 吸いこんで大きな声出して",
      "parts": [
        {"lyric": "(Hey! Hey!) shio no kaori suikonde ooki na koedashite",
          "range": [215.43, 218.35], "ans": []},
        {"lyric": "(Hey! Hey!) boku mo utau",
          "range": [218.35, 220.38], "ans": []}
      ]
    },
    {
      "lyric_jp": "エブリバディ！歌ってるとさ",
      "parts": [
        {"lyric": "Eburibadi!",
          "range": [222.11, 223.37], "ans": [4, 5, 6]},
        {"lyric": "Utatteru to sa",
          "range": [222.67, 224.74], "ans": []}
      ]
    },
    {"lyric": "(Hey! Hey!) sekai wa kirei na bouken wo misebirakasunda",
      "lyric_jp": "世界はキレイな冒険を見せびらかすんだ",
      "range": [224.74, 228.98], "ans": []},
    {"lyric": "(Hey! Hey!) utaeba omoidasu",
      "lyric_jp": "歌えば思い出す",
      "range": [228.98, 231.23], "ans": []},
    {
      "lyric_jp": "まだ！まだ！あきらめないと",
      "parts": [
        {"lyric": "Mada! Mada!",
          "range": [231.23, 232.4], "ans": [4, 5, 6]},
        {"lyric": "Akiramenai to",
          "range": [231.7, 233.58], "ans": []}
      ]
    },
    {"lyric": "(Hey! Hey!) oikakeru jibun de itai yo",
      "lyric_jp": "追いかける自分でいたいよ",
      "range": [233.58, 238.06], "ans": []},
    {
      "lyric_jp": "希望と言う帆を揚げて smile smile ship Start!",
      "parts": [
        {"lyric": "Kibou to iu ho wo agete",
          "range": [238.06, 240.58], "ans": [1]},
        {"lyric": "Smile smile ship Start!",
          "range": [239.88, 243.55], "ans": []},
        {"lyric": "(WANeTSUU*SURII!)",
          "range": [244.29, 246.32], "ans": []}
      ]
    },
    "",
    {
      "lyric_jp": "（ワン・ツー・スリー！）",
      "parts": [
        {"lyric": "(1, 2, 3!)",
          "range": [243.55, 249.17], "ans": []},
        {"lyric": "(Hey! Hey!)",
          "range": [249.17, 249.77], "ans": []},
        {"lyric": "(Hey! Hey!)",
          "range": [249.77, 250.37], "ans": []},
        {"lyric": "(Hey! Hey!)",
          "range": [250.37, 250.97], "ans": []},
        {"lyric": "(Hey! Hey!)",
          "range": [250.97, 251.57], "ans": []},
        {"lyric": "(Hey! Hey!)",
          "range": [251.57, 252.17], "ans": []},
        {"lyric": "(Hey! Hey!)",
          "range": [252.17, 252.77], "ans": []}
      ]
    }
  ]
}
